[
  {
    "date": "2026-03-16",
    "flights": [
      {"tail": "C-GAOX", "flight": "NS101", "origin": "CYZV", "dest": "CYUL", "block_hours": 2.8, "cycles": 1, "pilot_remarks": null},
      {"tail": "C-GAOX", "flight": "NS102", "origin": "CYUL", "dest": "CYZV", "block_hours": 2.8, "cycles": 1, "pilot_remarks": null},
      {"tail": "C-GBQX", "flight": "NS201", "origin": "CYZV", "dest": "CYQB", "block_hours": 1.9, "cycles": 1, "pilot_remarks": null},
      {"tail": "C-GBQX", "flight": "NS202", "origin": "CYQB", "dest": "CYZV", "block_hours": 1.9, "cycles": 1, "pilot_remarks": null},
      {"tail": "C-GCRX", "flight": "NS301", "origin": "CYZV", "dest": "CYHZ", "block_hours": 3.2, "cycles": 1, "pilot_remarks": null},
      {"tail": "C-GCRX", "flight": "NS302", "origin": "CYHZ", "dest": "CYZV", "block_hours": 3.1, "cycles": 1, "pilot_remarks": null},
      {"tail": "C-GDRX", "flight": "NS401", "origin": "CYZV", "dest": "CYUL", "block_hours": 2.7, "cycles": 1, "pilot_remarks": "DIFF PRESS caution light at FL220, cleared after cabin pressure adjustment"},
      {"tail": "C-GDRX", "flight": "NS402", "origin": "CYUL", "dest": "CYZV", "block_hours": 2.8, "cycles": 1, "pilot_remarks": null},
      {"tail": "C-GERX", "flight": "NS501", "origin": "CYZV", "dest": "CYSJ", "block_hours": 2.1, "cycles": 1, "pilot_remarks": null},
      {"tail": "C-GERX", "flight": "NS502", "origin": "CYSJ", "dest": "CYZV", "block_hours": 2.2, "cycles": 1, "pilot_remarks": null},
      {"tail": "C-GFRX", "flight": "NS601", "origin": "CYZV", "dest": "CYYT", "block_hours": 3.5, "cycles": 1, "pilot_remarks": null},
      {"tail": "C-GFRX", "flight": "NS602", "origin": "CYYT", "dest": "CYZV", "block_hours": 3.6, "cycles": 1, "pilot_remarks": null}
    ]
  },
  {
    "date": "2026-03-17",
    "flights": [
      {"tail": "C-GAOX", "flight": "NS101", "origin": "CYZV", "dest": "CYUL", "block_hours": 2.8, "cycles": 1, "pilot_remarks": null},
      {"tail": "C-GAOX", "flight": "NS102", "origin": "CYUL", "dest": "CYZV", "block_hours": 2.9, "cycles": 1, "pilot_remarks": null},
      {"tail": "C-GBQX", "flight": "NS201", "origin": "CYZV", "dest": "CYQB", "block_hours": 1.8, "cycles": 1, "pilot_remarks": null},
      {"tail": "C-GBQX", "flight": "NS202", "origin": "CYQB", "dest": "CYZV", "block_hours": 2.0, "cycles": 1, "pilot_remarks": null},
      {"tail": "C-GCRX", "flight": "NS301", "origin": "CYZV", "dest": "CYHZ", "block_hours": 3.1, "cycles": 1, "pilot_remarks": null},
      {"tail": "C-GCRX", "flight": "NS302", "origin": "CYHZ", "dest": "CYZV", "block_hours": 3.2, "cycles": 1, "pilot_remarks": null},
      {"tail": "C-GDRX", "flight": "NS401", "origin": "CYZV", "dest": "CYUL", "block_hours": 2.8, "cycles": 1, "pilot_remarks": "DIFF PRESS caution again at FL220 — same as yesterday. MEL raised."},
      {"tail": "C-GDRX", "flight": "NS402", "origin": "CYUL", "dest": "CYZV", "block_hours": 2.7, "cycles": 1, "pilot_remarks": null},
      {"tail": "C-GERX", "flight": "NS501", "origin": "CYZV", "dest": "CYSJ", "block_hours": 2.2, "cycles": 1, "pilot_remarks": null},
      {"tail": "C-GERX", "flight": "NS502", "origin": "CYSJ", "dest": "CYZV", "block_hours": 2.1, "cycles": 1, "pilot_remarks": null},
      {"tail": "C-GFRX", "flight": "NS601", "origin": "CYZV", "dest": "CYYT", "block_hours": 3.6, "cycles": 1, "pilot_remarks": null},
      {"tail": "C-GFRX", "flight": "NS602", "origin": "CYYT", "dest": "CYZV", "block_hours": 3.5, "cycles": 1, "pilot_remarks": null}
    ]
  },
  {
    "date": "2026-03-18",
    "flights": [
      {"tail": "C-GAOX", "flight": "NS101", "origin": "CYZV", "dest": "CYUL", "block_hours": 2.9, "cycles": 1, "pilot_remarks": null},
      {"tail": "C-GAOX", "flight": "NS102", "origin": "CYUL", "dest": "CYZV", "block_hours": 2.8, "cycles": 1, "pilot_remarks": null},
      {"tail": "C-GBQX", "flight": "NS201", "origin": "CYZV", "dest": "CYQB", "block_hours": 1.9, "cycles": 1, "pilot_remarks": null},
      {"tail": "C-GCRX", "flight": "NS301", "origin": "CYZV", "dest": "CYHZ", "block_hours": 3.2, "cycles": 1, "pilot_remarks": null},
      {"tail": "C-GCRX", "flight": "NS302", "origin": "CYHZ", "dest": "CYZV", "block_hours": 3.0, "cycles": 1, "pilot_remarks": null},
      {"tail": "C-GDRX", "flight": "NS401", "origin": "CYZV", "dest": "CYUL", "block_hours": 2.8, "cycles": 1, "pilot_remarks": null},
      {"tail": "C-GDRX", "flight": "NS402", "origin": "CYUL", "dest": "CYZV", "block_hours": 2.9, "cycles": 1, "pilot_remarks": null},
      {"tail": "C-GERX", "flight": "NS501", "origin": "CYZV", "dest": "CYSJ", "block_hours": 2.1, "cycles": 1, "pilot_remarks": null},
      {"tail": "C-GERX", "flight": "NS502", "origin": "CYSJ", "dest": "CYZV", "block_hours": 2.2, "cycles": 1, "pilot_remarks": null},
      {"tail": "C-GFRX", "flight": "NS601", "origin": "CYZV", "dest": "CYYT", "block_hours": 3.4, "cycles": 1, "pilot_remarks": null},
      {"tail": "C-GFRX", "flight": "NS602", "origin": "CYYT", "dest": "CYZV", "block_hours": 3.6, "cycles": 1, "pilot_remarks": null}
    ]
  },
  {
    "date": "2026-03-29",
    "flights": [
      {"tail": "C-GAOX", "flight": "NS101", "origin": "CYZV", "dest": "CYUL", "block_hours": 2.8, "cycles": 1, "pilot_remarks": null},
      {"tail": "C-GAOX", "flight": "NS102", "origin": "CYUL", "dest": "CYZV", "block_hours": 2.9, "cycles": 1, "pilot_remarks": null},
      {"tail": "C-GBQX", "flight": "NS201", "origin": "CYZV", "dest": "CYQB", "block_hours": 1.9, "cycles": 1, "pilot_remarks": null},
      {"tail": "C-GBQX", "flight": "NS202", "origin": "CYQB", "dest": "CYZV", "block_hours": 2.0, "cycles": 1, "pilot_remarks": null},
      {"tail": "C-GCRX", "flight": "NS301", "origin": "CYZV", "dest": "CYHZ", "block_hours": 3.1, "cycles": 1, "pilot_remarks": "Slight vibration noted during cruise, ATA 71 area. No instruments affected. Log for review."},
      {"tail": "C-GCRX", "flight": "NS302", "origin": "CYHZ", "dest": "CYZV", "block_hours": 3.2, "cycles": 1, "pilot_remarks": null},
      {"tail": "C-GDRX", "flight": "NS401", "origin": "CYZV", "dest": "CYUL", "block_hours": 2.8, "cycles": 1, "pilot_remarks": null},
      {"tail": "C-GDRX", "flight": "NS402", "origin": "CYUL", "dest": "CYZV", "block_hours": 2.7, "cycles": 1, "pilot_remarks": null},
      {"tail": "C-GERX", "flight": "NS501", "origin": "CYZV", "dest": "CYSJ", "block_hours": 2.2, "cycles": 1, "pilot_remarks": null},
      {"tail": "C-GERX", "flight": "NS502", "origin": "CYSJ", "dest": "CYZV", "block_hours": 2.1, "cycles": 1, "pilot_remarks": null},
      {"tail": "C-GFRX", "flight": "NS601", "origin": "CYZV", "dest": "CYYT", "block_hours": 3.5, "cycles": 1, "pilot_remarks": null},
      {"tail": "C-GFRX", "flight": "NS602", "origin": "CYYT", "dest": "CYZV", "block_hours": 3.6, "cycles": 1, "pilot_remarks": null}
    ]
  }
]
